odoo10_addon_mail_outbound_static-10.0.1.0.0.99.dev6-py3.8-nspkg.pth
odoo/addons/mail_outbound_static/README.rst
odoo/addons/mail_outbound_static/__init__.py
odoo/addons/mail_outbound_static/__manifest__.py
odoo/addons/mail_outbound_static/i18n/mail_outbound_static.pot
odoo/addons/mail_outbound_static/models/__init__.py
odoo/addons/mail_outbound_static/models/ir_mail_server.py
odoo/addons/mail_outbound_static/readme/DESCRIPTION.rst
odoo/addons/mail_outbound_static/readme/ROADMAP.rst
odoo/addons/mail_outbound_static/readme/USAGE.rst
odoo/addons/mail_outbound_static/static/description/icon.png
odoo/addons/mail_outbound_static/static/description/index.html
odoo/addons/mail_outbound_static/tests/__init__.py
odoo/addons/mail_outbound_static/tests/test.msg
odoo/addons/mail_outbound_static/tests/test_ir_mail_server.py
odoo/addons/mail_outbound_static/views/ir_mail_server_view.xml
odoo10_addon_mail_outbound_static-10.0.1.0.0.99.dev6.dist-info/METADATA
odoo10_addon_mail_outbound_static-10.0.1.0.0.99.dev6.dist-info/WHEEL
odoo10_addon_mail_outbound_static-10.0.1.0.0.99.dev6.dist-info/namespace_packages.txt
odoo10_addon_mail_outbound_static-10.0.1.0.0.99.dev6.dist-info/top_level.txt
odoo10_addon_mail_outbound_static-10.0.1.0.0.99.dev6.dist-info/RECORD
